caffoa/__init__.py
caffoa/__main__.py
caffoa/base_writer.py
caffoa/body_type_filter.py
caffoa/content_parser.py
caffoa/converter.py
caffoa/duplication_handler.py
caffoa/function_writer.py
caffoa/interface_writer.py
caffoa/model.py
caffoa/model_parser.py
caffoa/model_writer.py
caffoa/object_parser.py
caffoa/openapi_file.py
caffoa/path_parser.py
caffoa/data/base/CaffoaClientError.cs
caffoa/data/base/ClientErrorTemplate.cs
caffoa/data/base/DateSerializer.cs
caffoa/data/base/FactoryInterfaceTemplate.cs
caffoa/data/base/FunctionMethod.cs
caffoa/data/base/FunctionSwitchTemplate.cs
caffoa/data/base/FunctionTemplate.cs
caffoa/data/base/GenericClientErrorTemplate.cs
caffoa/data/base/InterfaceMethod.cs
caffoa/data/base/InterfaceTemplate.cs
caffoa/data/base/ModelEnumPropertyTemplate.cs
caffoa/data/base/ModelInterfaceTemplate.cs
caffoa/data/base/ModelPropertyTemplate.cs
caffoa/data/base/ModelTemplate.cs
caffoa/data/v1/FunctionMethod.cs
caffoa/data/v1/FunctionTemplate.cs
caffoa/data/v1/InterfaceMethod.cs
caffoa/data/v1/InterfaceTemplate.cs
caffoa/data/v2/FunctionMethod.cs
caffoa/data/v2/FunctionTemplate.cs
caffoa/data/v2/InterfaceMethod.cs
caffoa/data/v2/InterfaceTemplate.cs
caffoa/data/v2/ModelTemplate.cs
caffoa-0.37.0.dist-info/LICENSE
caffoa-0.37.0.dist-info/METADATA
caffoa-0.37.0.dist-info/WHEEL
caffoa-0.37.0.dist-info/top_level.txt
caffoa-0.37.0.dist-info/RECORD
