Metadata-Version: 2.1
Name: caffoa
Version: 0.37.0
Summary: Create Azure Functions From Open Api (for C#)
Home-page: https://github.com/claasd/caffoa
Author: Claas Diederichs
Author-email: 
License: MIT
Platform: UNKNOWN
Classifier: Programming Language :: Python :: 3.6
Classifier: Programming Language :: Python :: 3.7
Classifier: Programming Language :: Python :: 3.8
Classifier: Programming Language :: Python :: 3.9
Classifier: License :: OSI Approved :: MIT License
Classifier: Operating System :: OS Independent
Requires-Python: >=3.6
License-File: LICENSE
Requires-Dist: prance
Requires-Dist: openapi-spec-validator
Requires-Dist: PyYaml
